canonical_loader/__init__.py
canonical_loader/base_canonical_loader.py
canonical_loader/canonic_convert_utils.py
canonical_loader/canonic_date_utils.py
canonical_loader/canonical_loader.py
canonical_loader/s3_canonical_loader.py
canonical_loader/simple_loder.py
canonical_loader/general_utils/__init__.py
canonical_loader/general_utils/canonic_convert_utils.py
canonical_loader/general_utils/canonic_date_utils.py
canonical_loader-0.2.4.dist-info/METADATA
canonical_loader-0.2.4.dist-info/WHEEL
canonical_loader-0.2.4.dist-info/top_level.txt
canonical_loader-0.2.4.dist-info/RECORD
