Metadata-Version: 2.1
Name: canonical-loader
Version: 0.2.4
Summary: A Python module for loading and managing canonical data files with standardized naming conventions
Home-page: https://github.com/nailen1/canonical_loader.git
Author: June Young Park
Author-email: juneyoungpaak@gmail.com
Keywords: canonical data loader file management standardization
Classifier: Programming Language :: Python :: 3
Classifier: License :: OSI Approved :: MIT License
Classifier: Operating System :: OS Independent
Requires-Python: >=3.6
Requires-Dist: shining-pebbles>=0.5.5
Requires-Dist: string-date-controller>=0.1.3
Requires-Dist: aws-s3-controller>=0.7.5
Requires-Dist: tqdm
